{
  "last_refresh": "2026-04-03T16:05:00Z",
  "market_date": "2026-04-02",
  "positions": [
    {
      "symbol": "ARM",
      "status": "active",
      "instrument": "OPTION",
      "tier": "B",
      "option_ticker": "O:ARM260417C00125000",
      "entry_date": "2026-03-19",
      "entry_price": 8.42,
      "current_price": 23.17,
      "stop_price": 4.21,
      "exit_date": "2026-04-07",
      "position_size": 6657,
      "shares_or_contracts": 7,
      "unrealized_pnl": 10325,
      "unrealized_pct": 175.18,
      "days_held": 11,
      "days_remaining": 2,
      "body_pct": 0.1497,
      "atr_change_3d": 0.0484
    },
    {
      "symbol": "NFLX",
      "status": "active",
      "instrument": "OPTION",
      "tier": "B",
      "option_ticker": "O:NFLX260515C00097000",
      "entry_date": "2026-03-31",
      "entry_price": 4.63,
      "current_price": 6.3,
      "stop_price": 2.315,
      "exit_date": "2026-04-17",
      "position_size": 6482,
      "shares_or_contracts": 14,
      "unrealized_pnl": 2338,
      "unrealized_pct": 36.07,
      "days_held": 2,
      "days_remaining": 11,
      "body_pct": 0.0969,
      "atr_change_3d": 0.1227
    },
    {
      "symbol": "JD",
      "status": "active",
      "instrument": "OPTION",
      "tier": "B",
      "option_ticker": "O:JD260515C00031000",
      "entry_date": "2026-04-01",
      "entry_price": 0.68,
      "current_price": 0.47,
      "stop_price": 0.34,
      "exit_date": "2026-04-20",
      "position_size": 6596,
      "shares_or_contracts": 97,
      "unrealized_pnl": -2037,
      "unrealized_pct": -30.88,
      "days_held": 2,
      "days_remaining": 12,
      "body_pct": 0.8875,
      "atr_change_3d": -0.0388
    },
    {
      "symbol": "MRK",
      "status": "active",
      "instrument": "OPTION",
      "tier": "B",
      "option_ticker": "O:MRK260515C00125000",
      "entry_date": "2026-04-02",
      "entry_price": 4.05,
      "current_price": 3.35,
      "stop_price": 2.025,
      "exit_date": "2026-04-21",
      "position_size": 6480,
      "shares_or_contracts": 16,
      "unrealized_pnl": -1120,
      "unrealized_pct": -17.28,
      "days_held": 1,
      "days_remaining": 13,
      "body_pct": -0.0208,
      "atr_change_3d": 0.0949
    }
  ],
  "pending_signals": [
    {
      "symbol": "CSCO",
      "z_score": 0.194,
      "body_pct": 0.895,
      "atr_change": -0.0152,
      "tier": "B",
      "instrument": "OPTION",
      "sizing_rule": "Tier B: $7K options \u2014 Min 1 contract",
      "recommended_size": 7000,
      "recommended_contracts": 1,
      "is_new_signal": true
    }
  ],
  "recently_closed": [
    {
      "symbol": "SPG",
      "exit_date": "2026-04-02",
      "entry_price": 178.5,
      "exit_price": 174.3,
      "net_pnl": -1868,
      "return_pct": -2.35,
      "exit_type": "TIME"
    },
    {
      "symbol": "VXX",
      "exit_date": "2026-04-01",
      "entry_price": 2.35,
      "exit_price": 1.64,
      "net_pnl": -4035,
      "return_pct": -30.21,
      "exit_type": "TIME"
    },
    {
      "symbol": "AMT",
      "exit_date": "2026-04-02",
      "entry_price": 2.37,
      "exit_price": 0.18,
      "net_pnl": -6144,
      "return_pct": -92.41,
      "exit_type": "TIME"
    },
    {
      "symbol": "LI",
      "exit_date": "2026-04-02",
      "entry_price": 0.68,
      "exit_price": 0.39,
      "net_pnl": -2844,
      "return_pct": -42.65,
      "exit_type": "TIME"
    },
    {
      "symbol": "WMT",
      "exit_date": "2026-04-02",
      "entry_price": 4.0,
      "exit_price": 2.41,
      "net_pnl": -2653,
      "return_pct": -39.75,
      "exit_type": "TIME"
    }
  ],
  "summary": {
    "total_positions": 4,
    "total_pending": 0,
    "total_unrealized": 9506,
    "realized_pnl": 5364112,
    "month_realized": -17544,
    "month_unrealized": 9506,
    "win_rate": 44.0,
    "profit_factor": 1.77,
    "year_realized": 349038
  },
  "risk_alerts": [
    {
      "type": "exit_soon",
      "symbol": "ARM",
      "days_remaining": 2
    },
    {
      "type": "near_stop",
      "symbol": "JD",
      "distance_pct": 27.9
    }
  ],
  "signals": [
    {
      "symbol": "AZN",
      "z_score": 3.3343,
      "slope": 0.06054,
      "quintile": 5,
      "body_pct": 0.726,
      "atr_change": 0.15,
      "tier": "A",
      "sizing_rule": "$13K options (Tier A) \u2014 Min 1 contract",
      "recommended_size": 13000,
      "recommended_contracts": 1,
      "is_new_signal": true
    },
    {
      "symbol": "SEDG",
      "z_score": 2.5459,
      "slope": 0.04368,
      "quintile": 5,
      "body_pct": -0.3993,
      "atr_change": 0.15,
      "tier": "C",
      "sizing_rule": "$33K position (Tier C Q2)",
      "recommended_size": 33000,
      "recommended_contracts": null,
      "is_new_signal": true
    },
    {
      "symbol": "OXY",
      "z_score": 2.457,
      "slope": 0.04178,
      "quintile": 5,
      "body_pct": -0.4454,
      "atr_change": 0.15,
      "tier": "C",
      "sizing_rule": "$33K position (Tier C Q2)",
      "recommended_size": 33000,
      "recommended_contracts": null,
      "is_new_signal": true
    },
    {
      "symbol": "ARM",
      "z_score": 2.0422,
      "slope": 0.03291,
      "quintile": 5,
      "body_pct": -0.1056,
      "atr_change": 0.15,
      "tier": "C",
      "sizing_rule": "$67K position (Tier C Q3)",
      "recommended_size": 67000,
      "recommended_contracts": null,
      "is_new_signal": true
    },
    {
      "symbol": "MPC",
      "z_score": 2.0385,
      "slope": 0.03283,
      "quintile": 5,
      "body_pct": -0.3658,
      "atr_change": 0.15,
      "tier": "C",
      "sizing_rule": "$33K position (Tier C Q2)",
      "recommended_size": 33000,
      "recommended_contracts": null,
      "is_new_signal": true
    },
    {
      "symbol": "DVN",
      "z_score": 1.9564,
      "slope": 0.03107,
      "quintile": 5,
      "body_pct": -0.3885,
      "atr_change": 0.15,
      "tier": "C",
      "sizing_rule": "$33K position (Tier C Q2)",
      "recommended_size": 33000,
      "recommended_contracts": null,
      "is_new_signal": true
    },
    {
      "symbol": "EOG",
      "z_score": 1.9469,
      "slope": 0.03087,
      "quintile": 5,
      "body_pct": -0.3443,
      "atr_change": 0.15,
      "tier": "C",
      "sizing_rule": "$33K position (Tier C Q2)",
      "recommended_size": 33000,
      "recommended_contracts": null,
      "is_new_signal": true
    },
    {
      "symbol": "COP",
      "z_score": 1.9065,
      "slope": 0.03001,
      "quintile": 5,
      "body_pct": -0.1472,
      "atr_change": 0.15,
      "tier": "C",
      "sizing_rule": "$67K position (Tier C Q3)",
      "recommended_size": 67000,
      "recommended_contracts": null,
      "is_new_signal": true
    }
  ],
  "watchlist": [
    {
      "symbol": "HON",
      "quintile": 4,
      "z_score": 0.6988,
      "slope": 0.00418,
      "approaching": true,
      "sma50_slope": 0.4177,
      "body_pct": 0.4768,
      "distance_to_q5": "close"
    },
    {
      "symbol": "ADI",
      "quintile": 4,
      "z_score": 0.6964,
      "slope": 0.00412,
      "approaching": true,
      "sma50_slope": 0.4124,
      "body_pct": 0.6773,
      "distance_to_q5": "close"
    },
    {
      "symbol": "WMT",
      "quintile": 4,
      "z_score": 0.686,
      "slope": 0.0039,
      "approaching": true,
      "sma50_slope": 0.3902,
      "body_pct": 0.3657,
      "distance_to_q5": "close"
    },
    {
      "symbol": "NOC",
      "quintile": 4,
      "z_score": 0.684,
      "slope": 0.00386,
      "approaching": true,
      "sma50_slope": 0.386,
      "body_pct": 0.1737,
      "distance_to_q5": "close"
    },
    {
      "symbol": "ENPH",
      "quintile": 4,
      "z_score": 0.668,
      "slope": 0.00352,
      "approaching": true,
      "sma50_slope": 0.3518,
      "body_pct": -0.5357,
      "distance_to_q5": "close"
    },
    {
      "symbol": "COST",
      "quintile": 4,
      "z_score": 0.6649,
      "slope": 0.00345,
      "approaching": true,
      "sma50_slope": 0.3451,
      "body_pct": 0.4145,
      "distance_to_q5": "close"
    },
    {
      "symbol": "REGN",
      "quintile": 4,
      "z_score": 0.6095,
      "slope": 0.00227,
      "approaching": true,
      "sma50_slope": 0.2266,
      "body_pct": -0.2067,
      "distance_to_q5": "close"
    },
    {
      "symbol": "MAR",
      "quintile": 4,
      "z_score": 0.5702,
      "slope": 0.00142,
      "approaching": true,
      "sma50_slope": 0.1425,
      "body_pct": 0.4328,
      "distance_to_q5": "close"
    },
    {
      "symbol": "HLT",
      "quintile": 4,
      "z_score": 0.5585,
      "slope": 0.00118,
      "approaching": true,
      "sma50_slope": 0.1176,
      "body_pct": 0.2011,
      "distance_to_q5": "close"
    },
    {
      "symbol": "MCD",
      "quintile": 4,
      "z_score": 0.5237,
      "slope": 0.00043,
      "approaching": true,
      "sma50_slope": 0.0432,
      "body_pct": 0.0694,
      "distance_to_q5": "close"
    },
    {
      "symbol": "O",
      "quintile": 4,
      "z_score": 0.522,
      "slope": 0.00039,
      "approaching": true,
      "sma50_slope": 0.0394,
      "body_pct": -0.0114,
      "distance_to_q5": "close"
    },
    {
      "symbol": "TXN",
      "quintile": 4,
      "z_score": 0.5213,
      "slope": 0.00038,
      "approaching": true,
      "sma50_slope": 0.038,
      "body_pct": 0.4916,
      "distance_to_q5": "close"
    },
    {
      "symbol": "SPG",
      "quintile": 4,
      "z_score": 0.52,
      "slope": 0.00035,
      "approaching": true,
      "sma50_slope": 0.0353,
      "body_pct": 0.3679,
      "distance_to_q5": "close"
    },
    {
      "symbol": "CMCSA",
      "quintile": 4,
      "z_score": 0.5122,
      "slope": 0.00019,
      "approaching": true,
      "sma50_slope": 0.0185,
      "body_pct": -0.1888,
      "distance_to_q5": "close"
    },
    {
      "symbol": "HCA",
      "quintile": 4,
      "z_score": 0.4994,
      "slope": -9e-05,
      "approaching": false,
      "sma50_slope": -0.0088,
      "body_pct": 0.0785,
      "distance_to_q5": "moderate"
    }
  ],
  "as_of": "2026-04-02",
  "total_scanned": 225,
  "source": "pre_seeded_enriched_csv",
  "note": "Seeded from enriched CSV data as of 2026-04-02. Updates when Python engine runs at market close."
}